{
  "posts": [
    {
  "IdariBilgiler": {
    "BeyannameId": "123456",
    "IdariBilgiler": {
      "Donem": {
        "DonemTipi": "AYLIK",
        "Yil": 2023,
        "Ay": "OCAK"
      },
      "VergiDairesiAd": "İstanbul Vergi Dairesi",
      "VergiDairesiKod": "34",
      "SubeAd": "Kadıköy Şubesi",
      "SubeKod": "123",
      "MerkezSubeMi": false
    },
    "MukellefVkn": "1234567890",
    "DuzeltmeBeyannamesiMi": false,
    "BeyannameDurum": "TASLAK",
    "BeyannameVersiyon": 1
  },
  "Sifat": {
    "Id": "1",
    "BeyannameId": "123456",
    "Tckn": "12345678901",
    "Vkn": "1234567890",
    "AdSoyadUnvan": "Ahmet Yılmaz",
    "Eposta": "ahmet.yilmaz@example.com",
    "Telefon": "5551234567",
    "Tip": "MUKELLEF"
  },
  "Duzenleyen": {
    "Id": "2",
    "BeyannameId": "123456",
    "AdSoyadUnvan": "Mehmet Demir",
    "Tckn": "98765432109",
    "Vkn": "0987654321",
    "Eposta": "mehmet.demir@example.com",
    "Telefon": "5559876543"
  },
  "DefterBilgileri": [
    {
      "Id": "3",
      "BeyannameId": "123456",
      "DefterSiraNo": 1,
      "DuzenlemeTarihi": "2023-01-15T00:00:00",
      "SozlesmeNo": "SÖZ123",
      "Aciklama": "Örnek defter bilgisi",
      "YurtDisindaDuzenlenmisMi": false,
      "ZamanAsimiMi": false
    }
  ],
  "DeftereBagliTurBilgileri": [
    {
      "Id": "4",
      "BeyannameId": "123456",
      "IslemTuru": {
        "Kod": "TUR001",
        "Ad": "Satış İşlemi"
      },
      "BagliTurMu": true,
      "DefterSiraNo": 1,
      "TurNo": "TUR123",
      "DevirVarMi": false,
      "AlinmasiGerekenVergi": 100.0,
      "IcerdigiBelliPara": 5000.0,
      "DamgaVergiOrani": 0.1,
      "MaktuTutari": 50.0,
      "NushaSayisi": 2,
      "DamgaVergisi": 10.0
    }
  ],
  "DeftereBagliTarafBilgileri": [
    {
      "Id": "5",
      "BeyannameId": "123456",
      "DefterSiraNo": 1,
      "KimlikNumarasi": "12345678901",
      "AdSoyadUnvan": "Ayşe Kaya"
    }
  ],
  "VergiBildirimi": {
    "BeyannameId": "123456",
    "SekmeBilgisiList": [
      {
        "BeyannameId": 123456,
        "SekmeAdi": "Vergi Bilgileri",
        "HataliMi": false,
        "Mesaj": "Başarılı",
        "DoldurulduMu": true
      }
    ]
  }
}
  ],
  "profile": {
    "name": "typicode"
  }
}
